{
  "version": "0.1.0",
  "name": "breeding_mint",
  "instructions": [
    {
      "name": "initialize",
      "accounts": [],
      "args": []
    },
    {
      "name": "mintNft",
      "accounts": [
        {
          "name": "mintOwner",
          "isMut": true,
          "isSigner": true
        },
        {
          "name": "mint",
          "isMut": true,
          "isSigner": false
        },
        {
          "name": "tokenProgram",
          "isMut": false,
          "isSigner": false
        },
        {
          "name": "metadata",
          "isMut": true,
          "isSigner": false
        },
        {
          "name": "accToken",
          "isMut": true,
          "isSigner": false
        },
        {
          "name": "tokenMetadataProgram",
          "isMut": false,
          "isSigner": false
        },
        {
          "name": "payer",
          "isMut": true,
          "isSigner": false
        },
        {
          "name": "systemProgram",
          "isMut": false,
          "isSigner": false
        },
        {
          "name": "rent",
          "isMut": false,
          "isSigner": false
        },
        {
          "name": "accMaster",
          "isMut": true,
          "isSigner": false
        },
        {
          "name": "maker",
          "isMut": true,
          "isSigner": false
        }
      ],
      "args": [
        {
          "name": "uri",
          "type": "string"
        },
        {
          "name": "name",
          "type": "string"
        },
        {
          "name": "symbol",
          "type": "string"
        }
      ]
    },
    {
      "name": "burnMyNft",
      "accounts": [
        {
          "name": "authority",
          "isMut": false,
          "isSigner": true
        },
        {
          "name": "mintAna",
          "isMut": true,
          "isSigner": false
        },
        {
          "name": "userAna",
          "isMut": true,
          "isSigner": false
        },
        {
          "name": "tokenProgram",
          "isMut": false,
          "isSigner": false
        }
      ],
      "args": []
    }
  ],
  "errors": [
    {
      "code": 6000,
      "name": "InvalidMetadataUri",
      "msg": "Invalid metadata uri"
    }
  ],
  "metadata": {
    "address": "Dj7xRc1rAcbTsbKhEuMQ6DjJe4CA5pYko13pN2poP6ZX"
  }
}